exc_handler/__init__.py
exc_handler-1.0.3.dist-info/METADATA
exc_handler-1.0.3.dist-info/WHEEL
exc_handler-1.0.3.dist-info/top_level.txt
exc_handler-1.0.3.dist-info/RECORD
